{
  "name": "player_avatars/turkiye/arda_guler.jpg",
  "bucket": "uefa2024-manager.appspot.com",
  "metageneration": 1,
  "generation": 1721296707836,
  "contentType": "image/jpeg",
  "storageClass": "STANDARD",
  "contentDisposition": "inline",
  "downloadTokens": [
    "448972ae-2c44-45a7-bb50-0da10ee1742b"
  ],
  "etag": "HMwM1DZx9cAruaWrQ653jW3CdTU",
  "customMetadata": {},
  "timeCreated": "2024-07-18T09:58:27.836Z",
  "updated": "2024-07-18T09:58:27.836Z",
  "size": 17452,
  "md5Hash": "iEtrW2r6zqOOosTZvujnGg==",
  "crc32c": "3685629321"
}