{
  "name": "player_avatars/austria/romano_schmid.jpg",
  "bucket": "uefa2024-manager.appspot.com",
  "metageneration": 1,
  "generation": 1721296412602,
  "contentType": "image/jpeg",
  "storageClass": "STANDARD",
  "contentDisposition": "inline",
  "downloadTokens": [
    "dda21aa4-e55b-49a2-987e-0b87fd41d19c"
  ],
  "etag": "qRxQTDtCUY9F+Fy3rgA+gPlq3uM",
  "customMetadata": {},
  "timeCreated": "2024-07-18T09:53:32.602Z",
  "updated": "2024-07-18T09:53:32.602Z",
  "size": 21861,
  "md5Hash": "JSV9dfiqkpW4SQwFwQ/+yQ==",
  "crc32c": "182255584"
}