{
  "name": "player_avatars/romania/george_puscas.jpg",
  "bucket": "uefa2024-manager.appspot.com",
  "metageneration": 1,
  "generation": 1721296616637,
  "contentType": "image/jpeg",
  "storageClass": "STANDARD",
  "contentDisposition": "inline",
  "downloadTokens": [
    "b4821ace-0cb1-4c88-bd96-caabed60eb59"
  ],
  "etag": "jNL4h97+nf8t5+P+0Wjttmg8PyQ",
  "customMetadata": {},
  "timeCreated": "2024-07-18T09:56:56.637Z",
  "updated": "2024-07-18T09:56:56.637Z",
  "size": 23016,
  "md5Hash": "vBK8c5qPdVmHYnBuijRdeg==",
  "crc32c": "3842506033"
}