{
  "name": "player_avatars/denmark/rasmus_kristensen.jpg",
  "bucket": "uefa2024-manager.appspot.com",
  "metageneration": 1,
  "generation": 1721296458336,
  "contentType": "image/jpeg",
  "storageClass": "STANDARD",
  "contentDisposition": "inline",
  "downloadTokens": [
    "71937760-2997-427d-b33f-4d2d8b419874"
  ],
  "etag": "fsXnpXqeZ7+F5Tq8amPSTwnOA6M",
  "customMetadata": {},
  "timeCreated": "2024-07-18T09:54:18.336Z",
  "updated": "2024-07-18T09:54:18.336Z",
  "size": 4297,
  "md5Hash": "G2QHX4mOCc49pS8vD9yNcA==",
  "crc32c": "2624251850"
}