{
  "name": "player_avatars/spain/mikel_merino.jpg",
  "bucket": "uefa2024-manager.appspot.com",
  "metageneration": 1,
  "generation": 1721296673881,
  "contentType": "image/jpeg",
  "storageClass": "STANDARD",
  "contentDisposition": "inline",
  "downloadTokens": [
    "f7a14995-9b70-4c52-ac27-3cfda1db946a"
  ],
  "etag": "S1lStFfMWXvVynmRLDx9ASqGrgA",
  "customMetadata": {},
  "timeCreated": "2024-07-18T09:57:53.881Z",
  "updated": "2024-07-18T09:57:53.881Z",
  "size": 21345,
  "md5Hash": "pqX9YuXkfQQPS8G3o+/2aQ==",
  "crc32c": "3084888801"
}