{
  "name": "player_avatars/england/kieran_trippier.jpg",
  "bucket": "uefa2024-manager.appspot.com",
  "metageneration": 1,
  "generation": 1721296479730,
  "contentType": "image/jpeg",
  "storageClass": "STANDARD",
  "contentDisposition": "inline",
  "downloadTokens": [
    "2bb3a26c-3a27-4332-a58e-284380d27576"
  ],
  "etag": "I/OCNJhe5dSYqjeoNNENoB9sQpo",
  "customMetadata": {},
  "timeCreated": "2024-07-18T09:54:39.730Z",
  "updated": "2024-07-18T09:54:39.730Z",
  "size": 18587,
  "md5Hash": "Wl2dUDQvpbI/p+/Z7oe3aA==",
  "crc32c": "1007678345"
}